<?xml version="1.0" encoding="utf-8"?>
<odoo>
    <data>
        <record id="estate_property_form" model="ir.ui.view">
            <field name="name">estate.property.form</field>
            <field name="model">estate.property</field>
            <field name="arch" type="xml">
                <form string="Property">
                   <sheet>
                       <h1>
                           <field name="name" nolabel="1"/>
                       </h1>
                       <group>
                           <group name="left_main_group">
                             <field name="postcode"/>
                             <field name="date_available" string="Available From"/>
                           </group>
                           <group name="right_main_group">
                             <field name="expected_price"/>
                             <field name="selling_price"/>
                           </group>
                           <notebook>
                               <page string="Description" name="description">
                                   <group>
                                       <field name="description" string="Description"/>
                                       <field name="bedrooms" string="Bedrooms"/>
                                       <field name="living_area" string="Living Area (sqm)"/>
                                       <field name="facades" string="Facades"/>
                                       <field name="garden" string="Garden"/>
                                       <field name="garden_area" string="Garden Area (sqm)"/>
                                       <field name="garden_orientation" string="Garden Orientation"/>
                                   </group>
                               </page>
                           </notebook>
                       </group>
                    </sheet>
                </form>
            </field>
        </record>

        <record id="estate_property_list" model="ir.ui.view">
            <field name="name">estate.property.list</field>
            <field name="model">estate.property</field>
            <field name="arch" type="xml">
                <tree create="1" delete="1" string="Properties">
                    <field name="name" string="Title"/>
                    <field name="postcode"/>
                    <field name="bedrooms"/>
                    <field name="living_area" string="Living Area (sqm)"/>
                    <field name="expected_price"/>
                    <field name="selling_price"/>
                    <field name="date_available" string="Available From"/>
                </tree>
            </field>
        </record>

        <record id="estate_property_search" model="ir.ui.view">
            <field name="name">estate.property.search</field>
            <field name="model">estate.property</field>
            <field name="arch" type="xml">
                <search string="Search property">
                    <field name="name" domain="[('name','ilike',self)]"/>
                    <field name="postcode" domain="[('postcode','ilike',self)]"/>
                    <field name="expected_price" domain="[('expected_price','>=',self)]" string="Expected price greater than"/>
                    <field name="selling_price" domain="[('selling_price','>=',self)]" string="Selling price greater than"/>
                    <filter name="expected_price" domain="[('expected_price','>=',1000)]" string="Expected price greater than 1000"/>
                    <filter name="selling_price" domain="[('selling_price','>=',1000)]" string="Selling price greater than 1000"/>
                    <group expand="0" string="Group By">
                        <filter name="postcode" domain="" context="{'group_by':'postcode'}"/>
                        <filter string="Bedrooms" name="bedrooms" domain="" context="{'group_by':'bedrooms'}"/>
                    </group>
                </search>
            </field>
        </record>

        <record id="estate_property_action" model="ir.actions.act_window">
            <field name="name">Real Estate</field>
            <field name="res_model">estate.property</field>
            <field name="view_mode">tree,form</field>
            <field name="search_view_id" ref="estate_property_search"/>
        </record>
    </data>
</odoo>